Metadata-Version: 1.1
Name: salesforce-oauth-request-yplan
Version: 1.1.1
Summary: Util package to drive Salesforce Oauth Web flow for testing.
Home-page: https://github.com/YPlan/salesforce-oauth-request
Author: YPlan
Author-email: julius@yplanapp.com
License: Copyright (c) 2013 Scott Persinger
